buggpt/__init__.py
buggpt/__main__.py
buggpt/cli.py
buggpt/constants.py
buggpt/cookies.py
buggpt/debug.py
buggpt/errors.py
buggpt/models.py
buggpt/typing.py
buggpt/version.py
buggpt/Provider/ARTA.py
buggpt/Provider/Blackbox.py
buggpt/Provider/Blackboxapi.py
buggpt/Provider/ChatGLM.py
buggpt/Provider/ChatGpt.py
buggpt/Provider/Chatai.py
buggpt/Provider/Cloudflare.py
buggpt/Provider/Copilot.py
buggpt/Provider/DDG.py
buggpt/Provider/DeepInfraChat.py
buggpt/Provider/DocsBot.py
buggpt/Provider/DuckDuckGo.py
buggpt/Provider/Dynaspark.py
buggpt/Provider/Free2GPT.py
buggpt/Provider/FreeGpt.py
buggpt/Provider/GizAI.py
buggpt/Provider/ImageLabs.py
buggpt/Provider/LMArenaBeta.py
buggpt/Provider/LambdaChat.py
buggpt/Provider/LegacyLMArena.py
buggpt/Provider/OIVSCodeSer0501.py
buggpt/Provider/OIVSCodeSer2.py
buggpt/Provider/OIVSCodeSer5.py
buggpt/Provider/PerplexityLabs.py
buggpt/Provider/Pi.py
buggpt/Provider/Pizzagpt.py
buggpt/Provider/PollinationsAI.py
buggpt/Provider/PollinationsImage.py
buggpt/Provider/PuterJS.py
buggpt/Provider/SearXNG.py
buggpt/Provider/TeachAnything.py
buggpt/Provider/WeWordle.py
buggpt/Provider/Websim.py
buggpt/Provider/You.py
buggpt/Provider/Yqcloud.py
buggpt/Provider/__init__.py
buggpt/Provider/base_provider.py
buggpt/Provider/helper.py
buggpt/Provider/audio/EdgeTTS.py
buggpt/Provider/audio/MarkItDown.py
buggpt/Provider/audio/OpenAIFM.py
buggpt/Provider/audio/__init__.py
buggpt/Provider/audio/gTTS.py
buggpt/Provider/har/__init__.py
buggpt/Provider/har/lmarena.ai.har
buggpt/Provider/hf/HuggingChat.py
buggpt/Provider/hf/HuggingFaceAPI.py
buggpt/Provider/hf/HuggingFaceInference.py
buggpt/Provider/hf/HuggingFaceMedia.py
buggpt/Provider/hf/__init__.py
buggpt/Provider/hf/models.py
buggpt/Provider/hf_space/BlackForestLabs_Flux1Dev.py
buggpt/Provider/hf_space/CohereForAI_C4AI_Command.py
buggpt/Provider/hf_space/DeepseekAI_JanusPro7b.py
buggpt/Provider/hf_space/G4F.py
buggpt/Provider/hf_space/Microsoft_Phi_4_Multimodal.py
buggpt-0.0.1.dist-info/LICENSE
buggpt-0.0.1.dist-info/METADATA
buggpt-0.0.1.dist-info/WHEEL
buggpt-0.0.1.dist-info/entry_points.txt
buggpt-0.0.1.dist-info/top_level.txt
buggpt-0.0.1.dist-info/RECORD
